{
	"name": "Screen Server Traffic Violation", 
	"type": "any", 
	"index": "logstash-*", 
	"timeframe": {
		"minutes": 1
	},
	"filter": [
		{
			"query": {
				"wildcard": {
					"tag": "kubernetes.var.log.containers.celery"
				}
			}
		}, 
		{
			"query": {
				"wildcard": {
					"log": "screenservertrafficviolation"
				}
			}
		}
	], 
	"alert": ["slack"],
	"slack_webhook_url": "https://hooks.slack.com/services/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",
	"slack_username_override": "celery-bot"
}

// test-webhook https://hooks.slack.com/services/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